<?xml version='1.0' encoding='utf-8'?>
<song xmlns="http://openlyrics.info/namespace/2009/song" version="0.8" createdIn="OpenLP 2.9.5" modifiedIn="OpenLP 2.9.5" modifiedDate="2025-09-13T12:00:00"><properties><titles><title>Jeevitha thrushnalanu - naadu</title><title>జీవిత తృష్ణలను - నాదు</title><title>595</title></titles><verseOrder>c1 v1 c1 v2 c1 v3 c1 v4 c1</verseOrder><authors><author>His Servant</author></authors><songbooks><songbook name="Zion Songs Telugu Roman" entry="595" /></songbooks></properties><lyrics><verse name="c1"><lines>{lang-eng}Jeevitha thrushnalanu naadu
Teerchumayyaa priya Yesunaadhaa{/lang-eng}</lines><lines>{lang-tel}జీవిత తృష్ణలను నాదు
తీర్చుమయ్యా ప్రియ యేసునాథా{/lang-tel}</lines></verse><verse name="v1"><lines>{lang-eng}Naa jeevaadaaramu neeve nee nunde jeevamu pravahinchu
Pravahinche ee nee jeevamutho prabhuvaa nannu nimpumu{/lang-eng}</lines><lines>{lang-tel}నా జీవాధారము నీవే నీ నుండే జీవము ప్రవహించు
ప్రవహించే ఈ నీ జీవముతో ప్రభువా నన్ను నింపుము{/lang-tel}</lines></verse><verse name="v2"><lines>{lang-eng}Naa shaanthi daatavu neeve shantamu neenunde vachunugaa
Nischalamaina nee shantamuto naa jeevitamunu nimpumu{/lang-eng}</lines><lines>{lang-tel}నా శాంతిదాతవు నీవే శాంతము నీనుండే వచ్చునుగా
నిశ్చలమైన నీ శాంతముతో నా జీవితమును నింపుము{/lang-tel}</lines></verse><verse name="v3"><lines>{lang-eng}Satyanandamunu neeve prabhu
Asamaanamu nee yaanandamegaa
Atyaananda bharituniga jesi nityamu nannu nimpumu{/lang-eng}</lines><lines>{lang-tel}సత్యానందమును నీవే ప్రభు అసమానము నీ యానందమేగా
అత్యానంద భరితునిగాజేసి నిత్యము నన్ను నింపుము{/lang-tel}</lines></verse><verse name="v4"><lines>{lang-eng}Parishudda jeevanandamu parishuddatanu naa kosgitivi
Niratamu naa jeevitamu dwaaraa lokamunu deevinchumu{/lang-eng}</lines><lines>{lang-tel}పరిశుద్ధ జీవానందము పరిశుద్ధతను నా కొసగితివి
నిరతము నా జీవితము ద్వారా లోకమును దీవించుము{/lang-tel}</lines></verse></lyrics></song>