<?xml version='1.0' encoding='utf-8'?>
<song xmlns="http://openlyrics.info/namespace/2009/song" version="0.8" createdIn="OpenLP 2.9.5" modifiedIn="OpenLP 2.9.5" modifiedDate="2025-09-13T12:00:00"><properties><titles><title>Ella vela landu</title><title>ఎల్ల వేళలందు</title><title>672</title></titles><verseOrder>c1 v1 c1 v2 c1 v3 c1 v4 c1 v5 c1 v6 c1 v7 c1</verseOrder><authors><author>His Servant</author></authors><songbooks><songbook name="Zion Songs Telugu Roman" entry="672" /></songbooks></properties><lyrics><verse name="c1"><lines>{lang-eng}Ella vela landu kasta kaalamandu
Vallabhundaa Yesu stutintun ellanu
Neeve naa kelledala vallapadade
Vivarimpa{/lang-eng}</lines><lines>{lang-tel}ఎల్ల వేళలందు కష్టకాలమందు
వల్లభుండా యేసు స్తుతింతున్
ఎల్లను నీవే నా కెల్లెడల
వల్లపడదే వివరింప{/lang-tel}</lines></verse><verse name="v1"><lines>{lang-eng}Vimochakudaa Vimochana meeve
Rakshakudavu naa rakshana neeve{/lang-eng}</lines><lines>{lang-tel}విమోచకుడా విమోచన మీవే
రక్షకుడవు నా రక్షణ నీవే{/lang-tel}</lines></verse><verse name="v2"><lines>{lang-eng}Srusti karthavu sahaayamu neeve
Istuda veevu thritwamu neeve{/lang-eng}</lines><lines>{lang-tel}సృష్టికర్తవు సహాయము నీవే
ఇష్టుడ వీవు త్రిత్వము నీవే{/lang-tel}</lines></verse><verse name="v3"><lines>{lang-eng}jnaanamu neeve naa paanamu neeve
Daanamu neeve naa gaanamu neeve{/lang-eng}</lines><lines>{lang-tel}జ్ఞానము నీవే నా పానము నీవే
దానము నీవే నా గానము నీవే{/lang-tel}</lines></verse><verse name="v4"><lines>{lang-eng}Jyotiyu neeve naa neetiyu neeve
Aadiyu neeve naa antamu neeve{/lang-eng}</lines><lines>{lang-tel}జ్యోతియు నీవే నా నీతియు నీవే
ఆదియు నీవే నా అంతము నీవే{/lang-tel}</lines></verse><verse name="v5"><lines>{lang-eng}Nityuda neeve naa satyunda neeve
Stotramu neeve naa netramu neeve{/lang-eng}</lines><lines>{lang-tel}నిత్యుడ నీవే నా సత్యుండ నీవే
స్తోత్రము నీవే నా నేత్రము నీవే{/lang-tel}</lines></verse><verse name="v6"><lines>{lang-eng}Jeevamu neeve naa devuda veeve
Paavana meeve naa kaavali neeve{/lang-eng}</lines><lines>{lang-tel}జీవము నీవే నా దేవుడ వీవే
పావన మీవే నా కావలి నీవే{/lang-tel}</lines></verse><verse name="v7"><lines>{lang-eng}Kaantiyu neeve naa shaantiyu neeve
Santasa meeve naa kantayu neeve{/lang-eng}</lines><lines>{lang-tel}కాంతియు నీవే నా శాంతియు నీవే
సంతస మీవే నా కంతయు నీవే{/lang-tel}</lines></verse></lyrics></song>