<?xml version='1.0' encoding='utf-8'?>
<song xmlns="http://openlyrics.info/namespace/2009/song" version="0.8" createdIn="OpenLP 2.9.5" modifiedIn="OpenLP 2.9.5" modifiedDate="2025-09-17T12:00:00"><properties><titles><title>மகிமை கனம் துதிவல்லமை</title><title>1072</title></titles><verseOrder>v1</verseOrder><authors><author>His Servant</author></authors><songbooks><songbook name="Zion Songs" entry="1072" /></songbooks></properties><lyrics><verse name="v1"><lines>{lang-tam}மகிமை கனம் துதிவல்லமை
ஆட்டுக்குட்டி யானவர்க்கே
இயேசு கிறிஸ்து எங்கள் மீட்பர்
அல்லேலூயா அல்லேலூயா
அல்லேலூயா ஸ்தோத்திரம்.{/lang-tam}</lines></verse><verse name="o1"><lines>{alt_number}1072{/alt_number}
{alt_number}1072{/alt_number}
</lines></verse></lyrics></song>