<?xml version='1.0' encoding='utf-8'?>
<song xmlns="http://openlyrics.info/namespace/2009/song" version="0.8" createdIn="OpenLP 2.9.5" modifiedIn="OpenLP 2.9.5" modifiedDate="2025-09-17T12:00:00"><properties><titles><title>Bhajiyimpa randi prabhu</title><title>భజియింప రండి ప్రభు</title><title>215</title><title>129</title><title>100</title></titles><verseOrder>c1 v1 c1 v2 c1 v3 c1 v4 c1 v5 c1</verseOrder><authors><author>His Servant</author></authors><songbooks><songbook name="Zion Songs" entry="215" /></songbooks></properties><lyrics><verse name="c1"><lines>{lang-eng}Bhajiyimpa randi prabhu yesuni
Aatma satyamulatho premaamayuni
Parama thandrini{/lang-eng}</lines><lines>{lang-tel}భజియింప రండి ప్రభుయేసుని
ఆత్మసత్యములతో ప్రేమామయుని పరమ తండ్రిని{/lang-tel}</lines><lines>{lang-tam}ஆராதிப்போம் வாரும் கர்த்தர் இயேசுவை
ஆவி, உண்மையோடும், ஆண்டவரை
அன்பின் பிதாவை.{/lang-tam}</lines><lines>{lang-hin}आओ हम भजेंजे प्यारे यीशु को,
आत्मा सच्चाई से प्रेमी पिता को, परमेश्वर को{/lang-hin}</lines></verse><verse name="v1"><lines>{lang-eng}Paapa ksamaapana manakitchenu
Manala vimochinche rakhtamutho
J ayamu jayamu mana prabhuke{/lang-eng}</lines><lines>{lang-tel}పాప క్షమాపణ మనకిచ్చెను
మనల విమోచించె రక్తముతో
జయము జయము మన ప్రభుకే{/lang-tel}</lines><lines>{lang-tam}பாவ மன்னிப்பளித்தார் அவர் நமக்கு
விடுவித்தார் இரத்தத்தால் சாபத்தினின்று
ஜெயம் கூறிடுவோம் சதா அவர்க்கே{/lang-tam}</lines><lines>{lang-hin}पापों की माफी उसने दी हम को,
छुटकारा लॉहू से दिया हम को,
जय जयकार, जय जयकार उसकी सदा हो{/lang-hin}</lines></verse><verse name="v2"><lines>{lang-eng}Aatma mandira pratyakshata nosagen
Netramu therachenu yesuni chooda
Aashcharya karudu sadaakaalamu{/lang-eng}</lines><lines>{lang-tel}ఆత్మమందిర ప్రత్యక్షత నొసగెన్
నేత్రము తెరచెను యేసుని చూడ
ఆశ్చర్యకరుడు సదాకాలము{/lang-tel}</lines><lines>{lang-tam}கண்களைத் திறந்தார் இயேசுவைக் காண
கண்டைந்தோம் ஆவியின் கட்டிடத்தை
அற்புதர், அற்புதர் சதா அவரே{/lang-tam}</lines><lines>{lang-hin}आँखे उसने खोली देखें यीशु को,
और हम ने देखा उस आत्मिक भजन को,
अद्भुत है, अद्भुत है, सदा प्रभु जो{/lang-hin}</lines></verse><verse name="v3"><lines>{lang-eng}Ghanatha ponda sadaa raajyamunitche
Swaastyamu ponda vaarasula maitimi
Hosanna hosanna vijayunike{/lang-eng}</lines><lines>{lang-tel}ఘనత పొంద సదా రాజ్యము నిచ్చె
స్వాస్థ్యము పొంద వారసులమైతిమి
హోసన్న హోసన్న విజయునికే{/lang-tel}</lines><lines>{lang-tam}சுதந்தரம் பெற்றிடப் பாத்திரரானோம்
அதிகாரம் பெற்று ராஜ்ஜியம் ஆள
ஓசன்னா, ஓசன்னா ஜெயராஜர்க்கே{/lang-tam}</lines><lines>{lang-hin}वारिम हम बने हैं मीरास पाने को,
सदा राज्य करेंगे आदर पाने को,
होशाना, होशाना जयवन्त राजा को{/lang-hin}</lines></verse><verse name="v4"><lines>{lang-eng}Jagamunu jayinche jeevitamu nitche
Siluva shakhtiche manalanu gaachegaa
Stutularpintumu mukhti daatake{/lang-eng}</lines><lines>{lang-tel}జగమును జయించే జీవితమునిచ్చె
సిలువ శక్తిచే మనలను గాచెగా
స్తుతులర్పింతుము ముక్తిదాతకే{/lang-tel}</lines><lines>{lang-tam}உலகத்தை ஜெயிக்கும் ஜீவியம் ஈந்தார்
சிலுவையின் சக்தியால் காத்தாரே நம்மை
துதிப்போம், துதிப்போம் கர்த்தர் இயேசுவை{/lang-tam}</lines><lines>{lang-hin}जयवन्त हमें किया जग को जीतने को,
क्रूस की शक्ति द्वारा सम्भाला हम को,
स्तुति हो, स्तुति हो, मुक्तिदाता को{/lang-hin}</lines></verse><verse name="v5"><lines>{lang-eng}Sanghamu prabhuni chera theri choochegaa
Sadaa kaala maayanatho nunda neppudu
Saagila padedamu srusti karthake{/lang-eng}</lines><lines>{lang-tel}సంఘము ప్రభుని చేర తేరిచూచెగా
సదాకాల మాయనతో నుండ నెప్పుడు
సాగిలపడెదము సృష్ఠికర్తకే{/lang-tel}</lines><lines>{lang-tam}கர்த்தருக்காக சபை காத்திருக்குதே
நித்தியமாய் அவரை நாம் அடைய
வந்தனம், வந்தனம் சிருஷ்டிகருக்கே{/lang-tam}</lines><lines>{lang-hin}मण्डली बाट जोहती है प्रभु से मिलने को,
सदा साथ रहेंगे पायेंगे उस को,
वन्दना, वन्दना, सृष्टिकर्ता को{/lang-hin}</lines></verse><verse name="o1"><lines>{alt_number}100{/alt_number}
{alt_number}129{/alt_number}
{alt_number}213{/alt_number}
{alt_number}184{/alt_number}
{alt_number}215{/alt_number}
</lines></verse></lyrics></song>