<?xml version='1.0' encoding='utf-8'?>
<song xmlns="http://openlyrics.info/namespace/2009/song" version="0.8" createdIn="OpenLP 2.9.5" modifiedIn="OpenLP 2.9.5" modifiedDate="2025-09-17T12:00:00"><properties><titles><title>Mahatmudaina naa prabhu</title><title>మహాత్ముడైన నా ప్రభు</title><title>286</title><title>306</title><title>265</title></titles><verseOrder>v1 v2 v3 v4 v5 v6</verseOrder><authors><author>His Servant</author></authors><songbooks><songbook name="Zion Songs" entry="286" /></songbooks></properties><lyrics><verse name="v1"><lines>{lang-eng}Mahatmudaina naa prabhu vichitra silvajuda naa aasthin
Nastambuganenchi garvambananga drokkudun{/lang-eng}</lines><lines>{lang-tel}మహాత్ముడైన నా ప్రభు విచిత్ర సిల్వజూడ నా
ఆస్తిన్ నష్టంబుగా నెంచి గర్వంబణంగ ద్రొక్కుదున్{/lang-tel}</lines><lines>{lang-tam}என் அருள் நாதா இயேசுவே,
சிலுவைக் காட்சி பார்க்கையில்,
பூலோக மேன்மை நஷ்டமே,
என்றுணர்ந்தேன் என் உள்ளத்தில்.{/lang-tam}</lines><lines>{lang-hin}जिस क्रूस पर यीशु मारा था, उस क्रूस पर ध्यान जब करता हूँ,
संसारी लाभ को माटी सा, और यश को निन्दा जानता हूँ{/lang-hin}</lines></verse><verse name="v2"><lines>{lang-eng}Nee silvagaka yodevaa denin bremimpaneeyaku
Nannavarinchu sarvamun nee silvaki thyajintunu{/lang-eng}</lines><lines>{lang-tel}నీ సిల్వగాక యోదేవా దేనిన్ బ్రేమింపనీయకు
నన్నావరించు సర్వమున్ నీ సిల్వకై త్యజింతును{/lang-tel}</lines><lines>{lang-tam}என் மீட்பர் சிலுவை அல்லால்
வேறெதை நான் பாராட்டுவேன்?
சிற்றின்பம் யாவும் அதினால்
தகாததென்று தள்ளுவேன்.{/lang-tam}</lines><lines>{lang-hin}मत फूल जा, मेरे मूरख मन ! इस लोक के सुख और संपत पर,
हो ख्रिस्त की मृत्यु से प्रसन्न और सारी आशा रख उस पर{/lang-hin}</lines></verse><verse name="v3"><lines>{lang-eng}Shirambu padahastamul soochinchu dhukha premalu
Marennadaina goodenaa vishaadha premaleegatin{/lang-eng}</lines><lines>{lang-tel}శిరంబు పాదహస్తమున్ సూచించు దుఃఖ ప్రేమలు
మరెన్నడైన గూడెనా విషాద ప్రేమలీగతిన్{/lang-tel}</lines><lines>{lang-tam}கை தலை காலிலும், இதோ!
பேரன்பும் துன்பும் கலந்தே
பாய்ந்தோடும் காட்சிபோல் உண்டோ?
முள் முடியும் ஒப்பற்றதே.{/lang-tam}</lines><lines>{lang-hin}देख, उसके सिर, हाथ, पाँव की घाव, यह कैसा दुःख, यह कैसा प्यार !
अनूठा है यह प्रेम स्वभाव, अनूप यह जग का तारणहार{/lang-hin}</lines></verse><verse name="v4"><lines>{lang-eng}Mundlan durmaargulallina kireetamesu kundinan
Yee Bhookireetamu lanni daanin dooranga jaalune{/lang-eng}</lines><lines>{lang-tel}ముండ్లన్ దుర్మార్గులల్లిన కిరీట మేసు కుండినన్
ఈ భూకిరీటములన్ని దానిన్ దూరంగ జాలునే{/lang-tel}</lines><lines>{lang-tam}சராசரங்கள் அனைத்தும்
அவ்வன்புக்கு எம்மாத்திரம்?
என் ஜீவன் சுகம் செல்வமும்
என் நேசருக்குப் பாத்தியம்.{/lang-tam}</lines><lines>{lang-hin}जग तीनों लोक दे सकता मैं इस प्रेम के योग्य न होता दान,
हे यीशु प्रिय आप को मैं समर्पित करता हूँ देह, प्राण{/lang-hin}</lines></verse><verse name="v5"><lines>{lang-eng}Lokambune narpinchinan ayogyamaina eeviyou vinthaina
Yesu premakai naa yaavajeevamiththunu{/lang-eng}</lines><lines>{lang-tel}లోకంబు నే నర్పించినన్ అయోగ్యమైన యీవియౌ
వింతైన యేసు ప్రేమకై నా యావజ్జీవమిత్తును{/lang-tel}</lines><lines>{lang-tam}மாந்தர்க்கு மீட்பைக் கஸ்தியால்
சம்பாதித்தீந்த இயேசுவே,
உமக்கு என்றும் தாசரால்
மா ஸ்தோத்திரம் உண்டாகவே.{/lang-tam}</lines></verse><verse name="v6"><lines>{lang-eng}Rakshimpabadda lokamaa rakshimpa chaavu pondina
Rakshakudesunu sadhaa raavambuthoda golvumaa{/lang-eng}</lines><lines>{lang-tel}రక్షింపబడ్డ లోకమా రక్షింప చావు పొందిన
రక్షకుడేసును సదా రావంబు తోడ గొల్వుమా{/lang-tel}</lines></verse><verse name="o1"><lines>{alt_number}265{/alt_number}
{alt_number}306{/alt_number}
{alt_number}283{/alt_number}
{alt_number}243{/alt_number}
{alt_number}286{/alt_number}
</lines></verse></lyrics></song>