<?xml version='1.0' encoding='utf-8'?>
<song xmlns="http://openlyrics.info/namespace/2009/song" version="0.8" createdIn="OpenLP 2.9.5" modifiedIn="OpenLP 2.9.5" modifiedDate="2025-09-17T12:00:00"><properties><titles><title>Santasillunu mee hrudayaalu</title><title>సంతసిల్లును మీ హృదయాలు</title><title>444</title></titles><verseOrder>c1 v1 c1 v2 c1 v3 c1 v4 c1 v5 c1 v6 c1 v7 c1</verseOrder><authors><author>His Servant</author></authors><songbooks><songbook name="Zion Songs" entry="444" /></songbooks></properties><lyrics><verse name="c1"><lines>{lang-eng}Santasillunu mee hrudayaalu (2)
Siyonu mahima joochi (2){/lang-eng}</lines><lines>{lang-tel}సంతసిల్లును మీ హృదయాలు
సీయోను మహిమజూచి (2){/lang-tel}</lines></verse><verse name="v1"><lines>{lang-eng}Sundara varudu Yesu prabhuvu sundara vathi
Siyonu shaashwata shobhaathishayamutho
Bhasillutanu joochi{/lang-eng}</lines><lines>{lang-tel}సుందర వరుడు యేసు ప్రభువు సుందరవతి సీయోను
శాశ్వత శోభాతిశయముతో భాసిల్లుటను జూచి{/lang-tel}</lines></verse><verse name="v2"><lines>{lang-eng}Neela maya nitya punaadulu melimi
Chchaayaa manulu soorya kaantha sughandhamulu
Pushya raaga nirmithamu{/lang-eng}</lines><lines>{lang-tel}నీలమయ నిత్య పునాదులు మేలిమి ఛాయామణులు
సూర్యకాంత సుగంధములు పుష్యరాగ నిర్మితము{/lang-tel}</lines></verse><verse name="v3"><lines>{lang-eng}Nitya mahimatho veligedu mutyaala gummamulu
Swatcha magu suvarna mayamu
Aashcharya nagaramu{/lang-eng}</lines><lines>{lang-tel}నిత్య మహిమతో వెలిగెడు ముత్యాల గుమ్మములు
స్వచ్ఛమగు సువర్ణమయము ఆశ్చర్య నగరము{/lang-tel}</lines></verse><verse name="v4"><lines>{lang-eng}Jeeva vrukshamu jeeva phalamulu jeevaamrutha
Paanamu kaanthi vanthamugaa meriseti
Vintalu golpu nagaramu{/lang-eng}</lines><lines>{lang-tel}జీవవృక్షము జీవఫలములు జీవామృతపానము
కాంతి వంతముగా మెరిసేటి వింతలుగొల్పు నగరము{/lang-tel}</lines></verse><verse name="v5"><lines>{lang-eng}Swarna samamu daani prajalu santosha
Sahitulu dootale vintha padunatlu
Khyathini kaligina vaaru{/lang-eng}</lines><lines>{lang-tel}స్వర్ణ సమము దాని ప్రజలు సంతోష సహితులు
దూతలే వింతపడునట్లు ఖ్యాతిని కలిగిన వారు{/lang-tel}</lines></verse><verse name="v6"><lines>{lang-eng}Mandira samrudhini vaaru thrupti nondu
Chunnaaru aananda pravaahamu nandu
Paanamu cheyu chunnaaru{/lang-eng}</lines><lines>{lang-tel}మందిర సమృద్ధిని వారు తృప్తి నొందుచున్నారు
ఆనంద ప్రవాహమునందు పానము చేయుచున్నారు{/lang-tel}</lines></verse><verse name="v7"><lines>{lang-eng}Devudu selavitchina yatti devoktulalo
Nedi jaruga kundaga poledu
Varusagaa neraveren{/lang-eng}</lines><lines>{lang-tel}దేవుడు సెలవిచ్చినయట్టి దేవో క్తులలో నేది
జరుగకుండగ పోలేదు వరుసగా నెరవేరెన్{/lang-tel}</lines></verse><verse name="o1"><lines>{alt_number}441{/alt_number}
{alt_number}381{/alt_number}
{alt_number}444{/alt_number}
</lines></verse></lyrics></song>