<?xml version='1.0' encoding='utf-8'?>
<song xmlns="http://openlyrics.info/namespace/2009/song" version="0.8" createdIn="OpenLP 2.9.5" modifiedIn="OpenLP 2.9.5" modifiedDate="2025-09-17T12:00:00"><properties><titles><title>मसीह के खून की जय,</title><title>684</title></titles><verseOrder>v1</verseOrder><authors><author>His Servant</author></authors><songbooks><songbook name="Zion Songs" entry="684" /></songbooks></properties><lyrics><verse name="v1"><lines>{lang-hin}मसीह के खून की जय,
जो बहता रहता है,
जो सदा बहता है,
उसमें धो के गुनाहगार,
पाक साफ हो जाता है{/lang-hin}</lines></verse><verse name="o1"><lines>{alt_number}684{/alt_number}
{alt_number}684{/alt_number}
</lines></verse></lyrics></song>