<?xml version='1.0' encoding='utf-8'?>
<song xmlns="http://openlyrics.info/namespace/2009/song" version="0.8" createdIn="OpenLP 2.9.5" modifiedIn="OpenLP 2.9.5" modifiedDate="2025-09-17T12:00:00"><properties><titles><title>सुन लो, सुन लो, ध्यान से सुन लो,</title><title>694</title></titles><verseOrder>c1 v1 c1 v2 c1 v3 c1 v4 c1 v5 c1</verseOrder><authors><author>His Servant</author></authors><songbooks><songbook name="Zion Songs" entry="694" /></songbooks></properties><lyrics><verse name="c1"><lines>{lang-hin}सुन लो, सुन लो, ध्यान से सुन लो,
कोई पुकार रहा है (2), बोझ से पुकार रहा है,
रात बहुत बीत गयी है, दिन निकलने पर है,
वह दिन अब आता ही है{/lang-hin}</lines></verse><verse name="v1"><lines>{lang-hin}समय को जानकर अभी तैयार होना है,
जागो उठो, अभी नीम्द से जागना है, प्रभु शरण आना है,
हव घड़ी अब तो आ पहुँची है, छुटकारा अब तो निकट है{/lang-hin}</lines></verse><verse name="v2"><lines>{lang-hin}इसलिए अब तो पाप से निश्चय बचना है,
सावधान रहो वह दिन फन्दा बन जाये, अचानक न आ जाये,
सारी पृथ्वी के लोगों के ऊपर प्रभु का दिन निकट अब है{/lang-hin}</lines></verse><verse name="v3"><lines>{lang-hin}जागते रहना और सदा प्रार्थना करना है,
योग्य अब बनो बचना सब घटनाओं से जो जग पर आ रही है,
मसीह के सन्मुख खड़ा होना है, न्याय का सामना करना है{/lang-hin}</lines></verse><verse name="v4"><lines>{lang-hin}त्यागो उन कामों को, अंधकार से जो होते हैं,
हथियार बंधो ज्योति के जो सब हैं, शत्रु से लड़ना अब है,
दिन को जो सोहता वैसा ही करना, सीधी चाल चलना अब है{/lang-hin}</lines></verse><verse name="v5"><lines>{lang-hin}प्रभु यीशु को पहनकर तैयार रहना ही है,
वस्त्र उतारो जो मलिन हो गये है, लोहू से धुलवाना है,
गवाही को अपनी उज्ज्वल रखना है, क्योंकि प्रभु आता है{/lang-hin}</lines></verse><verse name="o1"><lines>{alt_number}694{/alt_number}
{alt_number}694{/alt_number}
</lines></verse></lyrics></song>