<?xml version='1.0' encoding='utf-8'?>
<song xmlns="http://openlyrics.info/namespace/2009/song" version="0.8" createdIn="OpenLP 2.9.5" modifiedIn="OpenLP 2.9.5" modifiedDate="2025-09-17T12:00:00"><properties><titles><title>Yesu prabhuve mahima</title><title>యేసుప్రభువే మహిమ</title><title>723</title><title>703</title><title>501</title></titles><verseOrder>c1 v1 c1 v2 c1 v3 c1 v4 c1 v5 c1 v6 c1</verseOrder><authors><author>His Servant</author></authors><songbooks><songbook name="Zion Songs" entry="723" /></songbooks></properties><lyrics><verse name="c1"><lines>{lang-eng}Yesu prabhuve mahima
Nireekshana manalo unnaadu
Jaya dwanulatho harshinchedamu
Prabhuve nireekshana{/lang-eng}</lines><lines>{lang-tel}యేసుప్రభువే మహిమ నిరీక్షణ మనలో వున్నాడు
జయధ్వనులతో హర్షించెదము ప్రభువే నిరీక్షణ{/lang-tel}</lines><lines>{lang-tam}கர்த்தர் இயேசுவே மகிமை நம்பிக்கையாய்
நமக்குள் வசிக்கிறவர்
ஜெயகீதங்களால் ஆனந்தம் கொள்ளுவோம்
கர்த்தரே நம்பிக்கையே{/lang-tam}</lines><lines>{lang-hin}मसीह हमारी महिमा की आशा, वह जो हम में है, (2)
जय जय लरते, खुशी मनाते (2), यीशु की आशा है  (2){/lang-hin}</lines></verse><verse name="v1"><lines>{lang-eng}Ee nirekshanache rakshana kalige
Vidipinchenu manala jeevapu
Nireekshana manakitchutaku
Krotha janmamu nosage{/lang-eng}</lines><lines>{lang-tel}ఈ నిరీక్షణచే రక్షణకలిగె విడిపించెను మనల
జీవపు నిరీక్షణ మనకిచ్చుటకు క్రొత్తజన్మను నొసగె{/lang-tel}</lines><lines>{lang-tam}இந்த நம்பிக்கையால் நாம் இரட்சிப்பும்
விடுதலையும் பெற்றோம்
மறுபிறப்பளித்தார் மா வல்ல கர்த்தர்
ஜீவனின் நம்பிக்கையாய்{/lang-tam}</lines><lines>{lang-hin}उसी आशा में उद्धार जो हुआ, हम को छुड़ाया है, (2)
नया जन्म जो दिया है हम को, जीवित आशा के लिए  (2){/lang-hin}</lines></verse><verse name="v2"><lines>{lang-eng}Manala nentho preminchi
Prabhuvu shubha nireekshana nitche
Anantha kaala dayanu joopi
Aayane stira parachen{/lang-eng}</lines><lines>{lang-tel}మనలనెంతో ప్రేమించి ప్రభువు శుభనిరీక్షణ నిచ్చె
అనంతకాల దయను జూపి ఆయనే స్థిరపరచెన్{/lang-tel}</lines><lines>{lang-tam}அநாதி சிநேகத்தால் அன்பு கூர்ந்தார்
நன் நம்பிக்கை அளித்தார்
நித்திய இரக்க உருக்கங்களால்
நம்மை ஸ்திரப்படுத்தினார்{/lang-tam}</lines><lines>{lang-hin}जिसने हम से, प्रेम किया है, उत्तम वह आशा दी है,
अनन्त शान्ति और अनुग्रह से, स्थिर भी वह किया है{/lang-hin}</lines></verse><verse name="v3"><lines>{lang-eng}Kristese manaku sarvaadhikaari
Mana maayana gruhamu
Antamu varaku stiramuga nilichi
Mana maanandintumu{/lang-eng}</lines><lines>{lang-tel}క్రీస్తేసే మనకు సర్వాధికారి మనమాయన గృహము
అంతమువరకు స్థిరముగ నిలిచి మనమానందింతుము{/lang-tel}</lines><lines>{lang-tam}கிறிஸ்துவானவரே நம் சர்வாதிகாரி
நாமே அவரின் குடும்பம்
முடிவு மட்டும் நாம் ஸ்திரமாய் நின்று
களிகூறுவோம் அவரில்{/lang-tam}</lines><lines>{lang-hin}मसीह हमारा अधिकारी है, उसका घर हम हैं,
अन्त तक यदि हम, साहस में रहें, आशा का आनन्द मनाऍँ{/lang-hin}</lines></verse><verse name="v4"><lines>{lang-eng}Ee nireekshananu kaligina vaare
Shuddhi parachu konduru
Sari jesi konudi aayanatho kooda
Samaanu lagu natlu{/lang-eng}</lines><lines>{lang-tel}ఈ నిరీక్షణను కలిగినవారే శుద్ధిపరచుకొందురు
సరిజేసికొనుడి ఆయనతో కూడ సమానులగునట్లు{/lang-tel}</lines><lines>{lang-tam}இந்த நம்பிக்கையை அடைந்தோர் யாவரும்
சுத்திகரித்துக் கொள்வார்
நாமும் அவருக்கு ஒப்பாயிருக்கும்படி
நம்மை சீர்ப்படுத்திக் கொள்வோம்{/lang-tam}</lines><lines>{lang-hin}जो कोई उस पर, आशा रखता है, खुद को शुद्ध करता है,
आओ जांचे हम, अपने आपको, उस के समान होना है{/lang-hin}</lines></verse><verse name="v5"><lines>{lang-eng}Prabhuvu itchchina ee nireekshana
Langaru vantidi nishchalamugaa
Stiramugaa mimmu prabhu
Chenta cherchunu gaa{/lang-eng}</lines><lines>{lang-tel}ప్రభువుయిచ్చిన ఈ నిరీక్షణ లంగరువంటిది
నిశ్చలముగా స్థిరముగ మిమ్ము ప్రభుచెంత చేర్చునుగా{/lang-tel}</lines><lines>{lang-tam}கர்த்தர் நமக்கு அளித்த நம்பிக்கை
ஆத்ம நங்கூரமானது
அந்த நம்பிக்கை நம்மை, உறுதியுமாய் நிறுத்தி
கர்த்தரிடம் சேர்க்கும்.{/lang-tam}</lines><lines>{lang-hin}आशा जो हम को प्रभु ने दी है, प्राण का वह लंगर है,
बहुत ही दृढ़ और, ऐसी निश्चित है, प्रभु तक पहुँचती है{/lang-hin}</lines></verse><verse name="v6"><lines>{lang-eng}Prabhu Yesu mahimatho
Vachchu nappudu manalanu
Koni povunu shubha pradha nireekshana
Kaligina manamu eduru choochedamu{/lang-eng}</lines><lines>{lang-tel}ప్రభు యేసు మహిమతో వచ్చునప్పుడు మనలను కొనిపోవును
శుభప్రదనిరీక్షణ కలిగిన మనము ఎదురుచూచెదము{/lang-tel}</lines><lines>{lang-tam}மகிமையுள்ளவராய் அவர் வெளிப்படுவார்
நம்மையும் அழைத்துக்கொள்வார்
ஆசீர்வாதமாம் நம்பிக்கையோடே
நாம் எதிர் நோக்கிடுவோம்.{/lang-tam}</lines><lines>{lang-hin}प्रगट वह होगा, महिमा में अपनी, हम को साथ ले जाएगा,
धन्य आशा, दी है कमको, बाट उसकी जोह रहे हैं{/lang-hin}</lines></verse><verse name="o1"><lines>{alt_number}501{/alt_number}
{alt_number}703{/alt_number}
{alt_number}707{/alt_number}
{alt_number}605{/alt_number}
{alt_number}723{/alt_number}
</lines></verse></lyrics></song>