<?xml version='1.0' encoding='utf-8'?>
<song xmlns="http://openlyrics.info/namespace/2009/song" version="0.8" createdIn="OpenLP 2.9.5" modifiedIn="OpenLP 2.9.5" modifiedDate="2025-09-17T12:00:00"><properties><titles><title>எந்நாளுமே துதிப்பாய்</title><title>850</title></titles><verseOrder>c1 v1 c1 v2 c1 v3 c1 v4 c1 v5 c1 v6 c1</verseOrder><authors><author>His Servant</author></authors><songbooks><songbook name="Zion Songs" entry="850" /></songbooks></properties><lyrics><verse name="c1"><lines>{lang-tam}எந்நாளுமே துதிப்பாய்
என்னாத்துமாவே நீ
எந்நாளுமே துதிப்பாய்
இந்நாள் வரையில் உன்னதனார் செய்த
எண்ணில்லா நன்மைகள் யாவு மறவாது.{/lang-tam}</lines></verse><verse name="v1"><lines>{lang-tam}பாவங்கள் எத்தனையோ
நினையாதிருந்தாருன்
பாவங்கள் எத்தனையோ
பாழான நோயை அகற்றிக் குணமாக்கிப்
பாரினில் வைத்த மா தயவை எண்ணி{/lang-tam}</lines></verse><verse name="v2"><lines>{lang-tam}எத்தனையோ கிருபை
உன்னுயிர்க்குச் செய்தாரே
எத்தனையோ கிருபை
நித்தமுனை முடி சூட்டினது மன்றி
நேயமதாக ஜீவனை மீட்டதால்{/lang-tam}</lines></verse><verse name="v3"><lines>{lang-tam}நன்மையாலுன் வாயை
நிறைத்தாரே பூர்த்தியாய்
நன்மையாலுன் வாயை
உன் வயது கழுகைப் போல் பலங்கொண்டு
ஒங்கு இளமை போலாகவே செய்ததால்{/lang-tam}</lines></verse><verse name="v4"><lines>{lang-tam}பூமிக்கும் வானத்துக்கும் உள்ள தூரம் போலவே
பூமிக்கும் வானத்துக்கும்
சாமி பயமுள்ளவர் மேல் அவர் அருள்
சாலவும் தங்குமே சத்திய மேயிது{/lang-tam}</lines></verse><verse name="v5"><lines>{lang-tam}மன்னிப்பு மாட்சிமையாய் மாதேவனருளும்
மன்னிப்பு மாட்சிமையாய்
எண்ணுவாயோ கிழக்கு மேற்கின் தூரமே
மண்ணில் உன் பாவம் அகன்றதத்தூரமே{/lang-tam}</lines></verse><verse name="v6"><lines>{lang-tam}தந்தை தன் பிள்ளைகட்கு தயவோடிரங்கானோ
தந்தை தன் பிள்ளைகட்கு
எந்த வேளையும் அவரோடு தங்கினால்
சொந்தம் பாராட்டியே தூக்கிச் சுமப்பாரே.{/lang-tam}</lines></verse><verse name="o1"><lines>{alt_number}850{/alt_number}
{alt_number}850{/alt_number}
</lines></verse></lyrics></song>