<?xml version='1.0' encoding='utf-8'?>
<song xmlns="http://openlyrics.info/namespace/2009/song" version="0.8" createdIn="OpenLP 2.9.5" modifiedIn="OpenLP 2.9.5" modifiedDate="2025-09-25T00:22:48"><properties><titles><title>Close to Thee</title><title>381</title></titles><verseOrder>v1 c1 v2 c2 v3 c3</verseOrder><authors><author>His Servant</author></authors><songbooks><songbook name="Christ in Song" entry="381" /></songbooks></properties><lyrics><verse name="c1"><lines>{lang-eng}Close to Thee, close to Thee,
Close to Thee, close to Thee;
All along my pilgrim journey,
Savior, let me walk with Thee.{/lang-eng}</lines></verse><verse name="c2"><lines>{lang-eng}Close to Thee, close to Thee,
Close to Thee, close to Thee;
Gladly will I toil and suffer,
Only let me walk with Thee.{/lang-eng}</lines></verse><verse name="c3"><lines>{lang-eng}Close to Thee, close to Thee,
Close to Thee, close to Thee;
Then the gate of life eternal
May I enter, Lord, with Thee.{/lang-eng}</lines></verse><verse name="v1"><lines>{lang-eng}Thou my everlasting Portion,
More than friend or life to me,
All along my pilgrim journey,
Savior, let me walk with Thee{/lang-eng}</lines></verse><verse name="v2"><lines>{lang-eng}Not for ease or worldly pleasure,
Not for fame my prayer shall be;
Gladly will I toil and suffer,
Only let me walk with Thee.{/lang-eng}</lines></verse><verse name="v3"><lines>{lang-eng}Lead me through the vale of shadows,
Bear me o’er life’s fitful sea;
Then the gate of life eternal
May I enter, Lord, with Thee.{/lang-eng}</lines></verse></lyrics></song>