<?xml version='1.0' encoding='UTF-8'?>
<song xmlns="http://openlyrics.info/namespace/2009/song" version="0.8" createdIn="OpenLP 3.1.1" modifiedIn="OpenLP 3.1.1" modifiedDate="2023-06-05T14:50:17">
  <properties>
    <titles>
      <title>The Lord Liveth</title>
    </titles>
    <verseOrder>v1 c1 c1</verseOrder>
    <authors>
      <author>Author Unknown</author>
    </authors>
  </properties>
  <lyrics>
    <verse name="v1">
      <lines>I will call upon the Lord<br/>Who is worthy to be praised<br/>So shall I be saved<br/>From my enemies</lines>
    </verse>
    <verse name="c1">
      <lines>The Lord liveth<br/>And blessed be my Rock<br/>Let the God of my salvation<br/>Be exalted</lines>
    </verse>
  </lyrics>
</song>
