<?xml version='1.0' encoding='utf-8'?>
<song xmlns="http://openlyrics.info/namespace/2009/song" version="0.8" createdIn="OpenLP 2.9.5" modifiedIn="OpenLP 2.9.5" modifiedDate="2025-09-19T23:10:24"><properties><titles><title>One Voice</title><title>2650</title></titles><verseOrder>v1 v2 v3</verseOrder><authors><author>His Servant</author></authors><songbooks><songbook name="Memphis Saints" entry="2650" /></songbooks></properties><lyrics><verse name="v1"><lines>{lang-eng}Father we ask of You this day
Come and heal our land
Knit our hearts together
That Your glory may be seen in us
Then the world will know that
Jesus Christ is Lord{/lang-eng}</lines></verse><verse name="v2"><lines>{lang-eng}Let us be one voice
That glorifies Your Name
Let us be one voice
Declaring that You reign
Let us be one voice in love and harmony
And we pray o God, grant us unity{/lang-eng}</lines></verse><verse name="v3"><lines>{lang-eng}Now is the time for you and I
To join our hearts in praise
That the name of Jesus
Will be lifted high above the earth
Then the world will know that
Jesus Christ is Lord{/lang-eng}</lines></verse></lyrics></song>