<?xml version='1.0' encoding='utf-8'?>
<song xmlns="http://openlyrics.info/namespace/2009/song" version="0.8" createdIn="OpenLP 2.9.5" modifiedIn="OpenLP 2.9.5" modifiedDate="2025-09-10T12:00:00"><properties><titles><title>Sodarudaa paapa kshamakai</title><title>సోదరుడా పాపక్షమకై</title><title>393</title></titles><verseOrder>c1 v1 c1 v2 c1 v3 c1 v4 c1 v5 c1</verseOrder><authors><author>His Servant</author></authors><songbooks><songbook name="Zion Songs Telugu" entry="393" /></songbooks></properties><lyrics><verse name="c1"><lines>{lang-tel}సోదరుడా పాపక్షమకై వేడుమా ప్రభు యేసుని{/lang-tel}</lines></verse><verse name="v1"><lines>{lang-tel}యేసుని రాజ్యము సమయము వచ్చెను
రక్షణను పొందెదవు నీవు విశ్వసించిన{/lang-tel}</lines></verse><verse name="v2"><lines>{lang-tel}మనుజరూపము ధరించి స్వర్గము దిగి వచ్చెను
తనదు రక్తముద్వారానే పాపబంధము త్రుంచెను{/lang-tel}</lines></verse><verse name="v3"><lines>{lang-tel}కలువరిలోని సిలువలో ప్రాణము నర్పించెను
ఎల్లరి పాపములకై తనదు రక్తము కార్చెను{/lang-tel}</lines></verse><verse name="v4"><lines>{lang-tel}సమయము లేదు సోదరా త్వరపడి రమ్ము వేగమే
సువార్తను విశ్వసించి రక్షణను పొందుము{/lang-tel}</lines></verse><verse name="v5"><lines>{lang-tel}పాప సాగరమునందు ఎంతకాలముందువు?
పాపసాగరమునుండి యేసుప్రభు విడిపించును{/lang-tel}</lines></verse></lyrics></song>