<?xml version='1.0' encoding='utf-8'?>
<song xmlns="http://openlyrics.info/namespace/2009/song" version="0.8" createdIn="OpenLP 2.9.5" modifiedIn="OpenLP 2.9.5" modifiedDate="2025-09-10T12:00:00"><properties><titles><title>Parishudda agnini pampu devaa</title><title>పరిశుద్ధ అగ్నిని పంపు దేవా</title><title>562</title></titles><verseOrder>v1 v2 v3 v4 v5 v6 v7</verseOrder><authors><author>His Servant</author></authors><songbooks><songbook name="Zion Songs Telugu" entry="562" /></songbooks></properties><lyrics><verse name="v1"><lines>{lang-tel}పరిశుద్ధ అగ్నిని పంపు దేవా (2)
రాజిల్లి వ్యాపింపజేయు దేవా (2){/lang-tel}</lines></verse><verse name="v2"><lines>{lang-tel}కరుణతో అగ్నికణములను
కరిగించి హృదయము తాకించుము{/lang-tel}</lines></verse><verse name="v3"><lines>{lang-tel}దేశమెల్లడలను దివ్యాగ్నిచే
దోషమెల్లను కాల్చి వేయుటకు{/lang-tel}</lines></verse><verse name="v4"><lines>{lang-tel}కన్యక వృద్ధులు యౌవనులు
ఉన్నత ఆత్మచే నింపబడన్{/lang-tel}</lines></verse><verse name="v5"><lines>{lang-tel}పాపులు పశ్చాత్తాపపడన్
శుద్ధుల మలినము పోగొట్టన్{/lang-tel}</lines></verse><verse name="v6"><lines>{lang-tel}పాపము శాపము లన్నియును
భస్మమి కాలి నశించునట్లు{/lang-tel}</lines></verse><verse name="v7"><lines>{lang-tel}యేసుని ప్రేమను రుచిచూడను
విశ్వాసమునందు వర్థిల్లను{/lang-tel}</lines></verse></lyrics></song>